{
  "feature_columns": [
    "current_a"
  ],
  "sequence_length": 100,
  "hidden_size": 64,
  "num_layers": 2,
  "dropout": 0.2,
  "max_time_to_stall_s": 5.0,
  "history": [
    {
      "epoch": 1,
      "train_loss": 1.5416424346022362,
      "val_loss": 1.3510297237948878
    },
    {
      "epoch": 2,
      "train_loss": 1.5227226687943198,
      "val_loss": 1.3555759947211565
    },
    {
      "epoch": 3,
      "train_loss": 1.5202340304450703,
      "val_loss": 1.3578557992114701
    },
    {
      "epoch": 4,
      "train_loss": 1.5296705432024484,
      "val_loss": 1.3654228121027117
    },
    {
      "epoch": 5,
      "train_loss": 1.5602643938117833,
      "val_loss": 1.3786822367344125
    },
    {
      "epoch": 6,
      "train_loss": 1.565650264405623,
      "val_loss": 1.3552269953044311
    }
  ],
  "risk_threshold": 0.1
}